frii_site/__init__.py
frii_site/api.py
frii_site/exceptions.py
frii_site/perms.py
frii_site-0.1.2.dist-info/METADATA
frii_site-0.1.2.dist-info/WHEEL
frii_site-0.1.2.dist-info/RECORD
