Metadata-Version: 2.1
Name: frii-site
Version: 0.1.2
Summary: Library for contacting the frii.site API
Author: ctih
Author-email: nevalaonni@gmail.com
Requires-Python: >=3.12,<4.0
Classifier: Programming Language :: Python :: 3
Classifier: Programming Language :: Python :: 3.12
Requires-Dist: requests (>=2.32.3,<3.0.0)
